ocr4all_pixel_classifier_frontend/__init__.py
ocr4all_pixel_classifier_frontend/compute_image_normalizations.py
ocr4all_pixel_classifier_frontend/convert_colors.py
ocr4all_pixel_classifier_frontend/create_dataset_file.py
ocr4all_pixel_classifier_frontend/evaluate.py
ocr4all_pixel_classifier_frontend/find_segments.py
ocr4all_pixel_classifier_frontend/gen_masks.py
ocr4all_pixel_classifier_frontend/generate_color_map.py
ocr4all_pixel_classifier_frontend/inspect_color_map.py
ocr4all_pixel_classifier_frontend/main.py
ocr4all_pixel_classifier_frontend/migrate_model.py
ocr4all_pixel_classifier_frontend/predict.py
ocr4all_pixel_classifier_frontend/train.py
ocr4all_pixel_classifier_frontend/scripts/__init__.py
ocr4all_pixel_classifier_frontend-0.6.2.data/data/requirements.txt
ocr4all_pixel_classifier_frontend-0.6.2.dist-info/LICENSE
ocr4all_pixel_classifier_frontend-0.6.2.dist-info/LICENSE.Apache-2.0
ocr4all_pixel_classifier_frontend-0.6.2.dist-info/LICENSE.GPL-3.0-or-later
ocr4all_pixel_classifier_frontend-0.6.2.dist-info/METADATA
ocr4all_pixel_classifier_frontend-0.6.2.dist-info/WHEEL
ocr4all_pixel_classifier_frontend-0.6.2.dist-info/entry_points.txt
ocr4all_pixel_classifier_frontend-0.6.2.dist-info/top_level.txt
ocr4all_pixel_classifier_frontend-0.6.2.dist-info/RECORD
