Metadata-Version: 2.1
Name: ocr4all-pixel-classifier-frontend
Version: 0.6.2
Summary: UNKNOWN
Home-page: https://gitlab2.informatik.uni-wuerzburg.de/ocr4all-page-segmentation/ocr4all-pixel-classifier-frontend
Author: Christoph Wick, Alexander Hartelt, Alexander Gehrke
Author-email: christoph.wick@informatik.uni-wuerzburg.de, alexander.hartelt@informatik.uni-wuerzburg.de, alexander.gehrke@informatik.uni-wuerzburg.de
License: UNKNOWN
Keywords: OCR,page segmentation,pixel classifier
Platform: UNKNOWN
Classifier: Programming Language :: Python :: 3
Classifier: License :: OSI Approved :: GNU General Public License v3 or later (GPLv3+)
Classifier: License :: OSI Approved :: Apache Software License
Classifier: Intended Audience :: Science/Research
Classifier: Topic :: Scientific/Engineering :: Image Recognition
Requires-Dist: ocr4all-pixel-classifier (~=0.6)
Requires-Dist: ocr4all-pylib (~=0.2)
Requires-Dist: tqdm
Requires-Dist: pypagexml
Requires-Dist: numpy
Requires-Dist: tensorflow
